dcw_finder/__init__.py
dcw_finder/_accessory.py
dcw_finder/_blast.py
dcw_finder/_cluster.py
dcw_finder/_count.py
dcw_finder/_parse.py
dcw_finder/_profile.py
dcw_finder/_search.py
dcw_finder/_seqlib.py
dcw_finder/_target.py
dcw_finder/_utils.py
dcw_finder/_visualize.py
dcw_finder/main.py
dcw_finder-0.0.27.dist-info/METADATA
dcw_finder-0.0.27.dist-info/WHEEL
dcw_finder-0.0.27.dist-info/top_level.txt
dcw_finder-0.0.27.dist-info/RECORD
