Metadata-Version: 2.1
Name: dcw-finder
Version: 0.0.27
Summary: Package for detecting dcw gene cluster
Home-page: https://github.com/jrim42/gene-cluster
Author: jsrim
Author-email: comfortindex@naver.com
Classifier: Programming Language :: Python :: 3.6
Classifier: Programming Language :: Python :: 3.7
Classifier: Programming Language :: Python :: 3.8
Classifier: Programming Language :: Python :: 3.9
Requires-Python: >=3.6
Requires-Dist: pandas
Requires-Dist: matplotlib
